GPD/GPD.py
GPD/__init__.py
GPD/utils.py
GPD/features/__init__.py
GPD/features/graph.py
GPD/features/protein.py
GPD/parameters/20220607_random_3.pkl
GPD/parameters/__init__.py
fair_GPD-0.0.2.dist-info/METADATA
fair_GPD-0.0.2.dist-info/WHEEL
fair_GPD-0.0.2.dist-info/top_level.txt
fair_GPD-0.0.2.dist-info/RECORD
