Metadata-Version: 2.1
Name: fair-GPD
Version: 0.0.2
Summary: Graphormer Based Protein Sequence Design Package: GPD
Home-page: https://github.com/decodermu/GPD
Author: Junximu
Author-email: mujunxi@126.com
License: MIT
Keywords: GPD
Classifier: Development Status :: 3 - Alpha
Classifier: Intended Audience :: Developers
Classifier: Topic :: Software Development :: Build Tools
Classifier: License :: OSI Approved :: MIT License
Classifier: Programming Language :: Python :: 3
Classifier: Programming Language :: Python :: 3.8
Classifier: Programming Language :: Python :: 3.9
Requires-Python: >=3.8
Requires-Dist: mdtraj ==1.9.9
Requires-Dist: networkx ==3.1
Requires-Dist: torch ==1.12.1
